Shift_Register.v
module Shift_Register #(parameter N = 8) (clk, rst, load, din, dir, rin, q);

input clk, rst, load, dir, rin;
input [N-1 : 0] din;
output reg [N-1 : 0] q;

always @(posedge clk or posedge rst) begin
  if(rst) begin
    q <= 8'b00000000;
  end

  else if(load) begin
    q <= din;
  end

  else if(dir) begin
    q <= {q[N-2:0], rin};
  end

  else if(~dir) begin
    q <= {rin, q[N-1:1]};
  end  

end

endmodule

Shift_Register_tb.v
module Shift_Register_tb();

parameter N = 8;

reg clk, rst, load, dir, rin;
reg [N-1 : 0] din;
wire [N-1 : 0] q;

Shift_Register #(.N(N)) uut (
    .clk(clk),
    .rst(rst),
    .rin(rin),
    .q(q),
    .load(load),
    .din(din),
    .dir(dir)
);

initial begin
    $dumpfile("8_bit_Shift_Register_Simulation.vcd");
    $dumpvars(0);
end

initial begin

  rst = 1;
  clk = 0;
  rin = 1;
  load = 0;
  dir = 1;
  din = 8'b00000011;

  #30 rst = 0;
  #50 load = 1; 
  #20 load = 0; 

  #100 dir = 0;  
  //#100 dir = 1;  // Start shifting right

  #50 load = 1; 
  #20 load = 0; // Ensure load is only active briefly

  #2000 $finish();

end

always #10 clk = ~clk;

endmodule

8_bit_Shift_Register_Simulation.vcd
$date
	Sat Mar 22 02:20:33 2025
$end
$version
	Icarus Verilog
$end
$timescale
	1s
$end
$scope module Shift_Register_tb $end
$var wire 8 ! q [7:0] $end
$var parameter 32 " N $end
$var reg 1 # clk $end
$var reg 8 $ din [7:0] $end
$var reg 1 % dir $end
$var reg 1 & load $end
$var reg 1 ' rin $end
$var reg 1 ( rst $end
$scope module uut $end
$var wire 1 # clk $end
$var wire 8 ) din [7:0] $end
$var wire 1 % dir $end
$var wire 1 & load $end
$var wire 1 ' rin $end
$var wire 1 ( rst $end
$var parameter 32 * N $end
$var reg 8 + q [7:0] $end
$upscope $end
$upscope $end
$enddefinitions $end
$comment Show the parameter values. $end
$dumpall
b1000 *
b1000 "
$end
#0
$dumpvars
b0 +
b11 )
1(
1'
0&
1%
b11 $
0#
b0 !
$end
#10
1#
#20
0#
#30
b1 !
b1 +
1#
0(
#40
0#
#50
b11 !
b11 +
1#
#60
0#
#70
b111 !
b111 +
1#
#80
0#
1&
#90
b11 !
b11 +
1#
#100
0#
0&
#110
b111 !
b111 +
1#
#120
0#
#130
b1111 !
b1111 +
1#
#140
0#
#150
b11111 !
b11111 +
1#
#160
0#
#170
b111111 !
b111111 +
1#
#180
0#
#190
b1111111 !
b1111111 +
1#
#200
0#
0%
#210
b10111111 !
b10111111 +
1#
#220
0#
#230
b11011111 !
b11011111 +
1#
#240
0#
#250
b11 !
b11 +
1#
1&
#260
0#
#270
b10000001 !
b10000001 +
1#
0&
#280
0#
#290
b11000000 !
b11000000 +
1#
#300
0#
#310
b11100000 !
b11100000 +
1#
#320
0#
#330
b11110000 !
b11110000 +
1#
#340
0#
#350
b11111000 !
b11111000 +
1#
#360
0#
#370
b11111100 !
b11111100 +
1#
#380
0#
#390
b11111110 !
b11111110 +
1#
#400
0#
#410
b11111111 !
b11111111 +
1#
